oopsie/__init__.py
oopsie/__main__.py
oopsie/_cli.py
oopsie/py.typed
oopsie-0.1.0.dist-info/METADATA
oopsie-0.1.0.dist-info/WHEEL
oopsie-0.1.0.dist-info/entry_points.txt
oopsie-0.1.0.dist-info/RECORD
